ploomes_client/__init__.py
ploomes_client/collections/__init__.py
ploomes_client/collections/account.py
ploomes_client/collections/attachments.py
ploomes_client/collections/cities.py
ploomes_client/collections/comments.py
ploomes_client/collections/contacts.py
ploomes_client/collections/deals.py
ploomes_client/collections/documents.py
ploomes_client/collections/emails.py
ploomes_client/collections/fields.py
ploomes_client/collections/filters.py
ploomes_client/collections/images.py
ploomes_client/collections/interaction_records.py
ploomes_client/collections/products.py
ploomes_client/collections/roles.py
ploomes_client/collections/tables.py
ploomes_client/collections/tasks.py
ploomes_client/collections/users.py
ploomes_client/core/__init__.py
ploomes_client/core/async_ploomes_client.py
ploomes_client/core/ploomes_client.py
ploomes_client/core/response.py
ploomes_client/core/utils.py
ploomes_client/sessions/__init__.py
ploomes_client/sessions/session_manager.py
ploomes_api_client-0.2.149.dist-info/LICENSE
ploomes_api_client-0.2.149.dist-info/METADATA
ploomes_api_client-0.2.149.dist-info/WHEEL
ploomes_api_client-0.2.149.dist-info/top_level.txt
ploomes_api_client-0.2.149.dist-info/RECORD
