Metadata-Version: 2.1
Name: ploomes-api-client
Version: 0.2.149
Summary: Python client for the Ploomes API
Home-page: https://github.com/victorfigueredo/ploomes-api-client
Author: Victor Figueredo
Author-email: cto@filterfeed.com.br
License: UNKNOWN
Platform: UNKNOWN
Classifier: Development Status :: 3 - Alpha
Classifier: Intended Audience :: Developers
Classifier: License :: OSI Approved :: MIT License
Classifier: Programming Language :: Python :: 3
Classifier: Programming Language :: Python :: 3.6
Classifier: Programming Language :: Python :: 3.7
Classifier: Programming Language :: Python :: 3.8
Classifier: Programming Language :: Python :: 3.9
Requires-Python: >=3.6
Requires-Dist: requests
Requires-Dist: ratelimit
Requires-Dist: pandas
Requires-Dist: httpx
